tutorwagtail/__init__.py
tutorwagtail/plugin.py
tutor_wagtail-0.0.1.dist-info/METADATA
tutor_wagtail-0.0.1.dist-info/WHEEL
tutor_wagtail-0.0.1.dist-info/entry_points.txt
tutor_wagtail-0.0.1.dist-info/top_level.txt
tutor_wagtail-0.0.1.dist-info/RECORD
