Metadata-Version: 2.1
Name: tutor-wagtail
Version: 0.0.1
Summary: A Tutor plugin for wagtail
Home-page: UNKNOWN
Author: yzw
Author-email: 327874145@qq.com
License: AGPLv3
Platform: UNKNOWN
Classifier: Development Status :: 3 - Alpha
Classifier: Intended Audience :: Developers
Classifier: License :: OSI Approved :: GNU Affero General Public License v3
Classifier: Operating System :: OS Independent
Classifier: Programming Language :: Python
Classifier: Programming Language :: Python :: 3.5
Classifier: Programming Language :: Python :: 3.6
Classifier: Programming Language :: Python :: 3.7
Requires-Python: >=3.5
